LICENSE
README.md
setup.py
UniDock/__init__.py
UniDock/unidock.py
UniDock/ligandPrepare/__init__.py
UniDock/ligandPrepare/atom_type.py
UniDock/ligandPrepare/rotatable_bond.py
UniDock/ligandPrepare/topology_builder.py
UniDock/ligandPrepare/utils.py
UniDockTools.egg-info/PKG-INFO
UniDockTools.egg-info/SOURCES.txt
UniDockTools.egg-info/dependency_links.txt
UniDockTools.egg-info/entry_points.txt
UniDockTools.egg-info/requires.txt
UniDockTools.egg-info/top_level.txt