Metadata-Version: 2.1
Name: UniDockTools
Version: 1.0.3
Summary: UniDock, a GPU-accelerated molecular docking program developed by DP Technology
Author: DP BayMax
License: UNKNOWN
Platform: UNKNOWN
License-File: LICENSE
